StaticProgramAnalysisReadingListUclaCs232/README.md
StaticProgramAnalysisReadingListUclaCs232/__init__.py
StaticProgramAnalysisReadingListUclaCs232/__main__.py
StaticProgramAnalysisReadingListUclaCs232/file.pdf
StaticProgramAnalysisReadingListUclaCs232/index.html
static_program_analysis_reading_list_ucla_cs232-2024.3.2.0.dist-info/METADATA
static_program_analysis_reading_list_ucla_cs232-2024.3.2.0.dist-info/WHEEL
static_program_analysis_reading_list_ucla_cs232-2024.3.2.0.dist-info/entry_points.txt
static_program_analysis_reading_list_ucla_cs232-2024.3.2.0.dist-info/top_level.txt
static_program_analysis_reading_list_ucla_cs232-2024.3.2.0.dist-info/RECORD
